pytorch_kfp_components/__init__.py
pytorch_kfp_components/components/__init__.py
pytorch_kfp_components/components/base/__init__.py
pytorch_kfp_components/components/base/base_component.py
pytorch_kfp_components/components/base/base_executor.py
pytorch_kfp_components/components/mar/__init__.py
pytorch_kfp_components/components/mar/component.py
pytorch_kfp_components/components/mar/executor.py
pytorch_kfp_components/components/minio/__init__.py
pytorch_kfp_components/components/minio/component.py
pytorch_kfp_components/components/minio/executor.py
pytorch_kfp_components/components/trainer/__init__.py
pytorch_kfp_components/components/trainer/component.py
pytorch_kfp_components/components/trainer/executor.py
pytorch_kfp_components/components/trainer/generic_executor.py
pytorch_kfp_components/components/utils/__init__.py
pytorch_kfp_components/components/utils/argument_parsing.py
pytorch_kfp_components/components/visualization/__init__.py
pytorch_kfp_components/components/visualization/component.py
pytorch_kfp_components/components/visualization/executor.py
pytorch_kfp_components/types/__init__.py
pytorch_kfp_components/types/standard_component_specs.py
pytorch_kfp_components-0.1.0.dist-info/LICENSE
pytorch_kfp_components-0.1.0.dist-info/METADATA
pytorch_kfp_components-0.1.0.dist-info/WHEEL
pytorch_kfp_components-0.1.0.dist-info/top_level.txt
pytorch_kfp_components-0.1.0.dist-info/RECORD
